setup.py
foodsafetykorea/__init__.py
foodsafetykorea/command.py
foodsafetykorea/models.py
foodsafetykorea/utils.py
foodsafetykorea.egg-info/PKG-INFO
foodsafetykorea.egg-info/SOURCES.txt
foodsafetykorea.egg-info/dependency_links.txt
foodsafetykorea.egg-info/top_level.txt