Metadata-Version: 2.1
Name: foodsafetykorea
Version: 1.0.0
Summary: 평범한 중학생이 만든 비공식 foodsafetykorea를 이용한 학교 급식을 알려주는 패키지입니다.
Author: LUA9
Maintainer: LUA9
License: UNKNOWN
Platform: UNKNOWN
